{
  "image_name": "109.png",
  "image_width": 1024,
  "image_height": 512,
  "palette_definition": [
    "red",
    "yellow",
    "green",
    "blue"
  ],
  "seed_extraction_mode": "hue_palette",
  "coordinate_system": {
    "origin": "top-left",
    "x_direction": "right",
    "y_direction": "down",
    "description": "Polygon vertices use image pixel coordinates. Each points array implicitly represents a closed polygon boundary."
  },
  "detected_color_order_top_to_bottom": [
    "red",
    "green",
    "blue"
  ],
  "layers": [
    {
      "vertical_rank": "top",
      "color_name": "red",
      "seed_pixel_count": 8193,
      "polygon_count": 1,
      "polygons": [
        {
          "area_px": 8571.5,
          "points": [
            [
              65,
              217
            ],
            [
              65,
              263
            ],
            [
              71,
              269
            ],
            [
              81,
              268
            ],
            [
              90,
              275
            ],
            [
              94,
              282
            ],
            [
              93,
              287
            ],
            [
              97,
              291
            ],
            [
              96,
              296
            ],
            [
              102,
              301
            ],
            [
              102,
              305
            ],
            [
              112,
              316
            ],
            [
              117,
              314
            ],
            [
              126,
              321
            ],
            [
              130,
              319
            ],
            [
              134,
              319
            ],
            [
              138,
              322
            ],
            [
              146,
              321
            ],
            [
              153,
              326
            ],
            [
              160,
              324
            ],
            [
              167,
              327
            ],
            [
              175,
              324
            ],
            [
              185,
              329
            ],
            [
              194,
              340
            ],
            [
              212,
              348
            ],
            [
              216,
              348
            ],
            [
              220,
              345
            ],
            [
              225,
              347
            ],
            [
              229,
              344
            ],
            [
              236,
              350
            ],
            [
              240,
              348
            ],
            [
              249,
              353
            ],
            [
              254,
              352
            ],
            [
              258,
              355
            ],
            [
              263,
              353
            ],
            [
              270,
              356
            ],
            [
              273,
              355
            ],
            [
              271,
              351
            ],
            [
              254,
              342
            ],
            [
              248,
              335
            ],
            [
              242,
              336
            ],
            [
              228,
              329
            ],
            [
              211,
              308
            ],
            [
              204,
              294
            ],
            [
              195,
              290
            ],
            [
              190,
              291
            ],
            [
              181,
              285
            ],
            [
              167,
              286
            ],
            [
              157,
              283
            ],
            [
              146,
              271
            ],
            [
              132,
              251
            ],
            [
              125,
              246
            ],
            [
              117,
              244
            ],
            [
              113,
              240
            ],
            [
              105,
              241
            ],
            [
              95,
              237
            ],
            [
              91,
              233
            ],
            [
              82,
              231
            ],
            [
              69,
              220
            ],
            [
              68,
              216
            ]
          ]
        }
      ]
    },
    {
      "vertical_rank": "middle",
      "color_name": "green",
      "seed_pixel_count": 13179,
      "polygon_count": 1,
      "polygons": [
        {
          "area_px": 14141.5,
          "points": [
            [
              65,
              266
            ],
            [
              65,
              347
            ],
            [
              77,
              359
            ],
            [
              83,
              358
            ],
            [
              88,
              362
            ],
            [
              99,
              363
            ],
            [
              108,
              370
            ],
            [
              126,
              367
            ],
            [
              133,
              372
            ],
            [
              137,
              372
            ],
            [
              145,
              379
            ],
            [
              152,
              378
            ],
            [
              166,
              386
            ],
            [
              174,
              385
            ],
            [
              178,
              388
            ],
            [
              181,
              387
            ],
            [
              201,
              403
            ],
            [
              205,
              402
            ],
            [
              213,
              408
            ],
            [
              215,
              407
            ],
            [
              221,
              411
            ],
            [
              227,
              410
            ],
            [
              234,
              416
            ],
            [
              245,
              417
            ],
            [
              255,
              422
            ],
            [
              261,
              420
            ],
            [
              265,
              423
            ],
            [
              278,
              425
            ],
            [
              284,
              419
            ],
            [
              290,
              420
            ],
            [
              293,
              418
            ],
            [
              296,
              420
            ],
            [
              301,
              417
            ],
            [
              295,
              411
            ],
            [
              290,
              393
            ],
            [
              281,
              380
            ],
            [
              279,
              365
            ],
            [
              275,
              361
            ],
            [
              274,
              356
            ],
            [
              265,
              353
            ],
            [
              259,
              355
            ],
            [
              250,
              353
            ],
            [
              241,
              348
            ],
            [
              237,
              350
            ],
            [
              230,
              345
            ],
            [
              223,
              348
            ],
            [
              219,
              346
            ],
            [
              213,
              349
            ],
            [
              196,
              341
            ],
            [
              192,
              334
            ],
            [
              189,
              334
            ],
            [
              184,
              328
            ],
            [
              175,
              324
            ],
            [
              166,
              328
            ],
            [
              161,
              324
            ],
            [
              153,
              326
            ],
            [
              136,
              319
            ],
            [
              127,
              321
            ],
            [
              116,
              313
            ],
            [
              111,
              315
            ],
            [
              102,
              305
            ],
            [
              103,
              301
            ],
            [
              96,
              296
            ],
            [
              97,
              292
            ],
            [
              93,
              288
            ],
            [
              94,
              283
            ],
            [
              88,
              273
            ],
            [
              83,
              268
            ],
            [
              73,
              270
            ],
            [
              68,
              265
            ]
          ]
        }
      ]
    },
    {
      "vertical_rank": "bottom",
      "color_name": "blue",
      "seed_pixel_count": 10339,
      "polygon_count": 1,
      "polygons": [
        {
          "area_px": 10769.5,
          "points": [
            [
              65,
              351
            ],
            [
              65,
              433
            ],
            [
              67,
              435
            ],
            [
              339,
              435
            ],
            [
              341,
              433
            ],
            [
              321,
              413
            ],
            [
              302,
              416
            ],
            [
              297,
              420
            ],
            [
              282,
              420
            ],
            [
              277,
              425
            ],
            [
              269,
              421
            ],
            [
              255,
              422
            ],
            [
              247,
              417
            ],
            [
              241,
              418
            ],
            [
              233,
              415
            ],
            [
              229,
              410
            ],
            [
              222,
              412
            ],
            [
              217,
              407
            ],
            [
              212,
              407
            ],
            [
              209,
              403
            ],
            [
              202,
              403
            ],
            [
              196,
              400
            ],
            [
              182,
              387
            ],
            [
              175,
              384
            ],
            [
              167,
              387
            ],
            [
              161,
              381
            ],
            [
              158,
              382
            ],
            [
              148,
              378
            ],
            [
              145,
              380
            ],
            [
              139,
              375
            ],
            [
              137,
              370
            ],
            [
              134,
              371
            ],
            [
              130,
              368
            ],
            [
              108,
              370
            ],
            [
              100,
              363
            ],
            [
              97,
              364
            ],
            [
              86,
              359
            ],
            [
              77,
              359
            ],
            [
              68,
              351
            ]
          ]
        }
      ]
    }
  ]
}