{
  "image_name": "669.png",
  "image_width": 1024,
  "image_height": 512,
  "palette_definition": [
    "red",
    "yellow",
    "green",
    "blue"
  ],
  "seed_extraction_mode": "hue_palette",
  "coordinate_system": {
    "origin": "top-left",
    "x_direction": "right",
    "y_direction": "down",
    "description": "Polygon vertices use image pixel coordinates. Each points array implicitly represents a closed polygon boundary."
  },
  "detected_color_order_top_to_bottom": [
    "green",
    "yellow",
    "blue"
  ],
  "layers": [
    {
      "vertical_rank": "top",
      "color_name": "green",
      "seed_pixel_count": 20753,
      "polygon_count": 1,
      "polygons": [
        {
          "area_px": 22176.5,
          "points": [
            [
              65,
              197
            ],
            [
              65,
              277
            ],
            [
              71,
              282
            ],
            [
              79,
              279
            ],
            [
              99,
              297
            ],
            [
              99,
              300
            ],
            [
              104,
              305
            ],
            [
              103,
              308
            ],
            [
              115,
              316
            ],
            [
              114,
              323
            ],
            [
              121,
              327
            ],
            [
              124,
              336
            ],
            [
              127,
              335
            ],
            [
              132,
              342
            ],
            [
              140,
              343
            ],
            [
              159,
              354
            ],
            [
              158,
              357
            ],
            [
              166,
              361
            ],
            [
              175,
              374
            ],
            [
              180,
              373
            ],
            [
              188,
              377
            ],
            [
              195,
              375
            ],
            [
              200,
              381
            ],
            [
              208,
              381
            ],
            [
              214,
              378
            ],
            [
              224,
              380
            ],
            [
              250,
              390
            ],
            [
              256,
              395
            ],
            [
              263,
              391
            ],
            [
              270,
              394
            ],
            [
              278,
              392
            ],
            [
              285,
              396
            ],
            [
              295,
              396
            ],
            [
              293,
              376
            ],
            [
              288,
              367
            ],
            [
              289,
              359
            ],
            [
              279,
              330
            ],
            [
              280,
              320
            ],
            [
              273,
              304
            ],
            [
              274,
              296
            ],
            [
              269,
              285
            ],
            [
              254,
              281
            ],
            [
              241,
              281
            ],
            [
              220,
              274
            ],
            [
              208,
              276
            ],
            [
              198,
              272
            ],
            [
              184,
              271
            ],
            [
              174,
              266
            ],
            [
              159,
              250
            ],
            [
              148,
              243
            ],
            [
              142,
              235
            ],
            [
              126,
              228
            ],
            [
              110,
              212
            ],
            [
              103,
              209
            ],
            [
              85,
              209
            ],
            [
              71,
              197
            ]
          ]
        }
      ]
    },
    {
      "vertical_rank": "middle",
      "color_name": "yellow",
      "seed_pixel_count": 4039,
      "polygon_count": 1,
      "polygons": [
        {
          "area_px": 4180.0,
          "points": [
            [
              65,
              280
            ],
            [
              66,
              341
            ],
            [
              71,
              343
            ],
            [
              77,
              342
            ],
            [
              80,
              344
            ],
            [
              88,
              341
            ],
            [
              93,
              345
            ],
            [
              106,
              341
            ],
            [
              111,
              344
            ],
            [
              122,
              344
            ],
            [
              127,
              346
            ],
            [
              131,
              352
            ],
            [
              135,
              352
            ],
            [
              149,
              362
            ],
            [
              152,
              367
            ],
            [
              158,
              368
            ],
            [
              163,
              372
            ],
            [
              166,
              371
            ],
            [
              172,
              376
            ],
            [
              176,
              374
            ],
            [
              180,
              378
            ],
            [
              185,
              379
            ],
            [
              192,
              386
            ],
            [
              196,
              385
            ],
            [
              202,
              389
            ],
            [
              208,
              387
            ],
            [
              214,
              388
            ],
            [
              219,
              393
            ],
            [
              231,
              392
            ],
            [
              236,
              397
            ],
            [
              246,
              395
            ],
            [
              251,
              397
            ],
            [
              254,
              401
            ],
            [
              259,
              400
            ],
            [
              272,
              408
            ],
            [
              277,
              406
            ],
            [
              280,
              400
            ],
            [
              287,
              400
            ],
            [
              289,
              398
            ],
            [
              288,
              396
            ],
            [
              279,
              393
            ],
            [
              270,
              395
            ],
            [
              263,
              391
            ],
            [
              257,
              395
            ],
            [
              237,
              384
            ],
            [
              233,
              385
            ],
            [
              225,
              379
            ],
            [
              221,
              381
            ],
            [
              210,
              379
            ],
            [
              205,
              382
            ],
            [
              197,
              376
            ],
            [
              189,
              377
            ],
            [
              181,
              372
            ],
            [
              175,
              374
            ],
            [
              157,
              352
            ],
            [
              141,
              342
            ],
            [
              138,
              343
            ],
            [
              132,
              341
            ],
            [
              128,
              336
            ],
            [
              122,
              333
            ],
            [
              120,
              326
            ],
            [
              113,
              322
            ],
            [
              115,
              316
            ],
            [
              104,
              308
            ],
            [
              104,
              305
            ],
            [
              98,
              300
            ],
            [
              99,
              297
            ],
            [
              83,
              282
            ],
            [
              82,
              279
            ],
            [
              73,
              282
            ]
          ]
        }
      ]
    },
    {
      "vertical_rank": "bottom",
      "color_name": "blue",
      "seed_pixel_count": 14152,
      "polygon_count": 1,
      "polygons": [
        {
          "area_px": 14947.5,
          "points": [
            [
              65,
              342
            ],
            [
              65,
              433
            ],
            [
              67,
              435
            ],
            [
              335,
              434
            ],
            [
              328,
              424
            ],
            [
              309,
              406
            ],
            [
              293,
              397
            ],
            [
              286,
              401
            ],
            [
              281,
              400
            ],
            [
              277,
              407
            ],
            [
              272,
              408
            ],
            [
              259,
              399
            ],
            [
              255,
              401
            ],
            [
              250,
              397
            ],
            [
              238,
              397
            ],
            [
              233,
              393
            ],
            [
              221,
              394
            ],
            [
              214,
              388
            ],
            [
              209,
              387
            ],
            [
              203,
              389
            ],
            [
              195,
              385
            ],
            [
              192,
              386
            ],
            [
              176,
              375
            ],
            [
              173,
              376
            ],
            [
              159,
              368
            ],
            [
              153,
              368
            ],
            [
              135,
              351
            ],
            [
              131,
              351
            ],
            [
              126,
              345
            ],
            [
              113,
              345
            ],
            [
              109,
              342
            ],
            [
              94,
              344
            ],
            [
              90,
              341
            ],
            [
              85,
              343
            ],
            [
              76,
              341
            ],
            [
              73,
              343
            ],
            [
              67,
              340
            ]
          ]
        }
      ]
    }
  ]
}