{
  "source_image": "341.png",
  "canvas_size": {
    "width": 342,
    "height": 436
  },
  "coordinate_system": {
    "type": "original_canvas",
    "origin": "top-left",
    "x_direction": "right",
    "y_direction": "down"
  },
  "normalization_transform": {
    "scale": 1.103448275862069,
    "offset_x": 67.86206896551724,
    "offset_y": 16.0,
    "orig_width": 342,
    "orig_height": 436,
    "target_width": 512,
    "target_height": 512,
    "padding": 16
  },
  "layers": {
    "red": {
      "vertical_rank": "top",
      "polygon_count": 1,
      "polygons": [
        {
          "area_pixels": 14626.5,
          "points": [
            [
              65.375,
              181.25
            ],
            [
              65.375,
              287.28125
            ],
            [
              69.90625,
              295.4375
            ],
            [
              78.96875,
              299.0625
            ],
            [
              86.21875,
              306.3125
            ],
            [
              91.65625,
              305.40625
            ],
            [
              98.90625,
              309.03125
            ],
            [
              104.34375,
              306.3125
            ],
            [
              110.6875,
              309.9375
            ],
            [
              118.84375762939453,
              310.84375
            ],
            [
              128.81251525878906,
              309.9375
            ],
            [
              151.46876525878906,
              320.8125
            ],
            [
              161.43751525878906,
              319.0
            ],
            [
              174.12501525878906,
              324.4375
            ],
            [
              179.56251525878906,
              321.71875
            ],
            [
              194.06251525878906,
              326.25
            ],
            [
              211.28126525878906,
              324.4375
            ],
            [
              220.34376525878906,
              328.0625
            ],
            [
              225.78126525878906,
              325.34375
            ],
            [
              232.12501525878906,
              328.96875
            ],
            [
              236.65626525878906,
              327.15625
            ],
            [
              261.125,
              345.28125
            ],
            [
              265.65625,
              354.34375
            ],
            [
              274.71875,
              358.875
            ],
            [
              273.8125,
              367.9375
            ],
            [
              280.15625,
              373.375
            ],
            [
              282.875,
              384.25
            ],
            [
              287.40625,
              386.0625
            ],
            [
              282.875,
              371.5625
            ],
            [
              282.875,
              359.78125
            ],
            [
              278.34375,
              353.4375
            ],
            [
              275.625,
              330.78125
            ],
            [
              255.68751525878906,
              307.21875
            ],
            [
              252.06251525878906,
              299.0625
            ],
            [
              224.87501525878906,
              290.0
            ],
            [
              215.81251525878906,
              292.71875
            ],
            [
              199.50001525878906,
              284.5625
            ],
            [
              182.28126525878906,
              286.375
            ],
            [
              174.12501525878906,
              280.9375
            ],
            [
              156.90626525878906,
              277.3125
            ],
            [
              137.87501525878906,
              263.71875
            ],
            [
              107.96875,
              231.09375
            ],
            [
              105.25,
              222.03125
            ],
            [
              97.09375,
              212.0625
            ],
            [
              92.5625,
              194.84375
            ],
            [
              86.21875,
              184.875
            ],
            [
              77.15625,
              179.4375
            ]
          ]
        }
      ]
    },
    "yellow": {
      "vertical_rank": "middle",
      "polygon_count": 1,
      "polygons": [
        {
          "area_pixels": 14556.0,
          "points": [
            [
              65.375,
              289.09375
            ],
            [
              66.28125,
              332.59375
            ],
            [
              70.8125,
              332.59375
            ],
            [
              75.34375,
              336.21875
            ],
            [
              81.6875,
              334.40625
            ],
            [
              90.75,
              338.9375
            ],
            [
              105.25,
              335.3125
            ],
            [
              110.6875,
              339.84375
            ],
            [
              115.21875,
              337.125
            ],
            [
              120.65625762939453,
              342.5625
            ],
            [
              134.25001525878906,
              344.375
            ],
            [
              159.62501525878906,
              370.65625
            ],
            [
              165.06251525878906,
              370.65625
            ],
            [
              178.65626525878906,
              387.875
            ],
            [
              181.37501525878906,
              386.96875
            ],
            [
              188.62501525878906,
              393.3125
            ],
            [
              194.06251525878906,
              392.40625
            ],
            [
              210.37501525878906,
              402.375
            ],
            [
              216.71876525878906,
              402.375
            ],
            [
              223.06251525878906,
              406.0
            ],
            [
              227.59376525878906,
              404.1875
            ],
            [
              234.84376525878906,
              409.625
            ],
            [
              241.18751525878906,
              409.625
            ],
            [
              248.43751525878906,
              416.875
            ],
            [
              254.78126525878906,
              415.0625
            ],
            [
              265.65625,
              422.3125
            ],
            [
              273.8125,
              417.78125
            ],
            [
              282.875,
              419.59375
            ],
            [
              291.03125,
              418.6875
            ],
            [
              294.65625,
              414.15625
            ],
            [
              295.5625,
              409.625
            ],
            [
              291.03125,
              402.375
            ],
            [
              290.125,
              393.3125
            ],
            [
              281.0625,
              380.625
            ],
            [
              280.15625,
              371.5625
            ],
            [
              274.71875,
              367.9375
            ],
            [
              273.8125,
              357.0625
            ],
            [
              266.5625,
              355.25
            ],
            [
              264.75,
              353.4375
            ],
            [
              264.75,
              348.0
            ],
            [
              253.87501525878906,
              341.65625
            ],
            [
              247.53126525878906,
              333.5
            ],
            [
              239.37501525878906,
              328.0625
            ],
            [
              232.12501525878906,
              328.96875
            ],
            [
              226.68751525878906,
              326.25
            ],
            [
              220.34376525878906,
              328.0625
            ],
            [
              212.18751525878906,
              325.34375
            ],
            [
              189.53126525878906,
              326.25
            ],
            [
              179.56251525878906,
              321.71875
            ],
            [
              173.21876525878906,
              324.4375
            ],
            [
              162.34376525878906,
              319.0
            ],
            [
              155.09376525878906,
              321.71875
            ],
            [
              149.65626525878906,
              318.09375
            ],
            [
              142.40626525878906,
              318.09375
            ],
            [
              129.71876525878906,
              310.84375
            ],
            [
              119.75000762939453,
              310.84375
            ],
            [
              116.12500762939453,
              308.125
            ],
            [
              110.6875,
              309.9375
            ],
            [
              105.25,
              307.21875
            ],
            [
              99.8125,
              309.03125
            ],
            [
              93.46875,
              306.3125
            ],
            [
              88.03125,
              307.21875
            ],
            [
              78.0625,
              298.15625
            ],
            [
              75.34375,
              299.0625
            ],
            [
              69.0,
              294.53125
            ],
            [
              68.09375,
              288.1875
            ]
          ]
        }
      ]
    },
    "blue": {
      "vertical_rank": "bottom",
      "polygon_count": 1,
      "polygons": [
        {
          "area_pixels": 16434.5,
          "points": [
            [
              65.375,
              335.3125
            ],
            [
              65.375,
              433.1875
            ],
            [
              67.1875,
              435.0
            ],
            [
              340.875,
              434.09375
            ],
            [
              320.9375,
              413.25
            ],
            [
              307.34375,
              415.96875
            ],
            [
              297.375,
              412.34375
            ],
            [
              286.5,
              421.40625
            ],
            [
              272.0,
              418.6875
            ],
            [
              263.84375,
              422.3125
            ],
            [
              254.78126525878906,
              415.0625
            ],
            [
              248.43751525878906,
              416.875
            ],
            [
              239.37501525878906,
              408.71875
            ],
            [
              236.65626525878906,
              409.625
            ],
            [
              219.43751525878906,
              402.375
            ],
            [
              211.28126525878906,
              402.375
            ],
            [
              203.12501525878906,
              396.03125
            ],
            [
              201.31251525878906,
              396.9375
            ],
            [
              193.15626525878906,
              392.40625
            ],
            [
              190.43751525878906,
              393.3125
            ],
            [
              176.84376525878906,
              386.0625
            ],
            [
              165.06251525878906,
              370.65625
            ],
            [
              159.62501525878906,
              369.75
            ],
            [
              149.65626525878906,
              358.875
            ],
            [
              140.59376525878906,
              354.34375
            ],
            [
              134.25001525878906,
              344.375
            ],
            [
              121.56250762939453,
              344.375
            ],
            [
              116.12500762939453,
              337.125
            ],
            [
              99.8125,
              336.21875
            ],
            [
              94.375,
              338.9375
            ],
            [
              88.9375,
              335.3125
            ],
            [
              86.21875,
              337.125
            ],
            [
              79.875,
              334.40625
            ],
            [
              76.25,
              336.21875
            ],
            [
              73.53125,
              334.40625
            ]
          ]
        }
      ]
    }
  }
}